JingtongOmiKuangjia/README.md
JingtongOmiKuangjia/__init__.py
JingtongOmiKuangjia/__main__.py
JingtongOmiKuangjia/file.epub
JingtongOmiKuangjia/index.html
JingtongOmiKuangjia/css/__init__.py
JingtongOmiKuangjia/css/annotations.css
JingtongOmiKuangjia/css/main.css
JingtongOmiKuangjia/css/normalize.css
JingtongOmiKuangjia/css/popup.css
JingtongOmiKuangjia/font/__init__.py
JingtongOmiKuangjia/font/fontello.eot
JingtongOmiKuangjia/font/fontello.svg
JingtongOmiKuangjia/font/fontello.ttf
JingtongOmiKuangjia/font/fontello.woff
JingtongOmiKuangjia/img/__init__.py
JingtongOmiKuangjia/img/annotator-glyph-sprite.png
JingtongOmiKuangjia/img/annotator-icon-sprite.png
JingtongOmiKuangjia/img/apple-touch-icon.png
JingtongOmiKuangjia/img/cancelfullscreen.png
JingtongOmiKuangjia/img/close.png
JingtongOmiKuangjia/img/fullscreen.png
JingtongOmiKuangjia/img/loader.gif
JingtongOmiKuangjia/img/menu-icon.png
JingtongOmiKuangjia/img/save.png
JingtongOmiKuangjia/img/saved.png
JingtongOmiKuangjia/img/settings-s.png
JingtongOmiKuangjia/img/settings.png
JingtongOmiKuangjia/img/star.png
JingtongOmiKuangjia/js/__init__.py
JingtongOmiKuangjia/js/epub.js
JingtongOmiKuangjia/js/epub.min.js
JingtongOmiKuangjia/js/epub.min.map
JingtongOmiKuangjia/js/hooks.min.js
JingtongOmiKuangjia/js/hooks.min.map
JingtongOmiKuangjia/js/reader.js
JingtongOmiKuangjia/js/reader.js.map
JingtongOmiKuangjia/js/reader.min.js
JingtongOmiKuangjia/js/reader.min.map
JingtongOmiKuangjia/js/hooks/__init__.py
JingtongOmiKuangjia/js/hooks/extensions/__init__.py
JingtongOmiKuangjia/js/hooks/extensions/highlight.js
JingtongOmiKuangjia/js/libs/__init__.py
JingtongOmiKuangjia/js/libs/jquery.min.js
JingtongOmiKuangjia/js/libs/localforage.min.js
JingtongOmiKuangjia/js/libs/screenfull.js
JingtongOmiKuangjia/js/libs/screenfull.min.js
JingtongOmiKuangjia/js/libs/zip.min.js
JingtongOmiKuangjia/js/plugins/__init__.py
JingtongOmiKuangjia/js/plugins/hypothesis.js
JingtongOmiKuangjia/js/plugins/search.js
jingtong_omi_kuangjia-2024.3.2.0.dist-info/METADATA
jingtong_omi_kuangjia-2024.3.2.0.dist-info/WHEEL
jingtong_omi_kuangjia-2024.3.2.0.dist-info/entry_points.txt
jingtong_omi_kuangjia-2024.3.2.0.dist-info/top_level.txt
jingtong_omi_kuangjia-2024.3.2.0.dist-info/RECORD
